reproj/__init__.py
reproj/main.py
reproj-0.1.2.dist-info/LICENSE.txt
reproj-0.1.2.dist-info/METADATA
reproj-0.1.2.dist-info/WHEEL
reproj-0.1.2.dist-info/top_level.txt
reproj-0.1.2.dist-info/RECORD
