Metadata-Version: 2.1
Name: reproj
Version: 0.1.2
Summary: Reproject shapely geometries
Author-email: Seth Goodman <sgoodman@aiddata.wm.edu>
License: BSD-3-Clause
Project-URL: Source Code, https://github.com/sgoodm/python-reproj
Project-URL: Bug Tracker, https://github.com/sgoodm/python-reproj/issues
Keywords: projection,transform,vector,gis,geospatial,geographic
Classifier: Development Status :: 4 - Beta
Classifier: Intended Audience :: Developers
Classifier: Intended Audience :: Science/Research
Classifier: License :: OSI Approved :: BSD License
Classifier: Operating System :: OS Independent
Classifier: Programming Language :: Python :: 3.7
Classifier: Programming Language :: Python :: 3.8
Classifier: Programming Language :: Python :: 3.9
Classifier: Programming Language :: Python :: 3.10
Classifier: Programming Language :: Python :: 3.11
Classifier: Topic :: Utilities
Classifier: Topic :: Scientific/Engineering :: GIS
Requires-Python: >=3.7
License-File: LICENSE.txt
Requires-Dist: pyproj (>=2.1.0)
Requires-Dist: shapely
Provides-Extra: dev
Requires-Dist: reproj[test] ; extra == 'dev'
Requires-Dist: twine ; extra == 'dev'
Provides-Extra: test
Requires-Dist: coverage ; extra == 'test'
Requires-Dist: pytest (>=4.6) ; extra == 'test'
Requires-Dist: pytest-cov (>=2.2.0) ; extra == 'test'
Requires-Dist: fiona ; extra == 'test'
